mypack/__init__.py
mypack/clear.py
mypack/depickler.py
mypack/file_lister.py
mypack/fitro.py
mypack/intput.py
mypack/picklify.py
mypack/strintput.py
mypack_fabian-1.0.0.dist-info/License
mypack_fabian-1.0.0.dist-info/METADATA
mypack_fabian-1.0.0.dist-info/WHEEL
mypack_fabian-1.0.0.dist-info/top_level.txt
mypack_fabian-1.0.0.dist-info/RECORD
