Metadata-Version: 2.1
Name: mypack-fabian
Version: 1.0.0
Summary: Methods i use
Home-page: https://github.com/Dottyboi/MyPack
Author: Dotty
Author-email: fabian.pizarro.04@gmail.com
License: UNKNOWN
Platform: UNKNOWN
Classifier: Programming Language :: Python :: 3.10
Classifier: License :: OSI Approved :: MIT License
Classifier: Operating System :: OS Independent
Requires-Python: >=3.10
License-File: License
